[
  {
    "Full_Name": "Anaya Das",
    "Roll_Number": "DHT2023001",
    "University_Name": "Indian Institute of Digital Learning",
    "College_Name": "School of Humanities",
    "Degree": "B.Tech",
    "Branch_or_Specialization": "Marketing",
    "Year_of_Passing": 2025,
    "Certificate_Name": "Bachelor of Technology Degree Certificate",
    "Issue_Date": "2023-07-09",
    "Certificate_ID": "CERT-UNI-0001"
  },
  {
    "Full_Name": "Kunal Khan",
    "Roll_Number": "DHT2023002",
    "University_Name": "Indian Institute of Digital Learning",
    "College_Name": "School of Engineering",
    "Degree": "MBA",
    "Branch_or_Specialization": "Mechanical",
    "Year_of_Passing": 2023,
    "Certificate_Name": "Master of Business Administration Degree Certificate",
    "Issue_Date": "2023-07-13",
    "Certificate_ID": "CERT-UNI-0002"
  },
  {
    "Full_Name": "Anaya Das",
    "Roll_Number": "DHT2023003",
    "University_Name": "Global Tech University",
    "College_Name": "School of Commerce",
    "Degree": "M.Tech",
    "Branch_or_Specialization": "Computer Science",
    "Year_of_Passing": 2025,
    "Certificate_Name": "Master of Technology Degree Certificate",
    "Issue_Date": "2025-11-18",
    "Certificate_ID": "CERT-UNI-0003"
  },
  {
    "Full_Name": "Meera Khan",
    "Roll_Number": "DHT2023004",
    "University_Name": "National University of Technology",
    "College_Name": "School of Humanities",
    "Degree": "B.Tech",
    "Branch_or_Specialization": "Marketing",
    "Year_of_Passing": 2024,
    "Certificate_Name": "Bachelor of Technology Degree Certificate",
    "Issue_Date": "2025-07-05",
    "Certificate_ID": "CERT-UNI-0004"
  },
  {
    "Full_Name": "Aditya Singh",
    "Roll_Number": "DHT2023005",
    "University_Name": "National University of Technology",
    "College_Name": "School of Humanities",
    "Degree": "BBA",
    "Branch_or_Specialization": "Marketing",
    "Year_of_Passing": 2025,
    "Certificate_Name": "Bachelor of Business Administration Degree Certificate",
    "Issue_Date": "2025-06-29",
    "Certificate_ID": "CERT-UNI-0005"
  },
  {
    "Full_Name": "_iddharth Nair",
    "Roll_Number": "DHT2023006",
    "University_Name": "Eastern Institute of Engineering",
    "College_Name": "School of Sciences",
    "Degree": "MBA",
    "Branch_or_Specialization": "Biotechnology",
    "Year_of_Passing": 2025,
    "Certificate_Name": "Master of Business Administration Degree Certificate",
    "Issue_Date": "2023-01-11",
    "Certificate_ID": "CERT-UNI-0006"
  },
  {
    "Full_Name": "Kunal Das",
    "Roll_Number": "DHT2023007",
    "University_Name": "National University of Technology",
    "College_Name": "School of Engineering",
    "Degree": "MBA",
    "Branch_or_Specialization": "Finance",
    "Year_of_Passing": 2023,
    "Certificate_Name": "Master of Business Administration Degree Certificate",
    "Issue_Date": "2024-12-02",
    "Certificate_ID": "CERT-UNI-0007"
  },
  {
    "Full_Name": "Ishita Sharma",
    "Roll_Number": "DHT2023008",
    "University_Name": "Global Tech University",
    "College_Name": "School of Engineering",
    "Degree": "MBA",
    "Branch_or_Specialization": "Biotechnology",
    "Year_of_Passing": 2023,
    "Certificate_Name": "Master of Business Administration Degree Certificate",
    "Issue_Date": "2025-05-23",
    "Certificate_ID": "CERT-UNI-0008"
  },
  {
    "Full_Name": "Meera Verma",
    "Roll_Number": "DHT2023009",
    "University_Name": "Bright Future Institute",
    "College_Name": "School of Sciences",
    "Degree": "B.Sc",
    "Branch_or_Specialization": "Mechanical",
    "Year_of_Passing": 2023,
    "Certificate_Name": "Bachelor of Science Degree Certificate",
    "Issue_Date": "2024-03-21",
    "Certificate_ID": "CERT-UNI-0009"
  },
  {
    "Full_Name": "Aarav Patel",
    "Roll_Number": "DHT2023010",
    "University_Name": "Global Tech University",
    "College_Name": "School of Sciences",
    "Degree": "M.Tech",
    "Branch_or_Specialization": "Marketing",
    "Year_of_Passing": 2025,
    "Certificate_Name": "Master of Technology Degree Certificate",
    "Issue_Date": "2023-08-21",
    "Certificate_ID": "CERT-UNI-0010"
  },
  {
    "Full_Name": "Riya Singh",
    "Roll_Number": "DHT2023011",
    "University_Name": "Indian Institute of Digital Learning",
    "College_Name": "School of Engineering",
    "Degree": "B.Tech",
    "Branch_or_Specialization": "Electrical",
    "Year_of_Passing": 2022,
    "Certificate_Name": "Bachelor of Technology Degree Certificate",
    "Issue_Date": "2025-04-06",
    "Certificate_ID": "CERT-UNI-0011"
  },
  {
    "Full_Name": "Vivaan Patel",
    "Roll_Number": "DHT2023012",
    "University_Name": "Bright Future Institute",
    "College_Name": "School of Management",
    "Degree": "M.Tech",
    "Branch_or_Specialization": "Civil Engineering",
    "Year_of_Passing": 2022,
    "Certificate_Name": "Master of Technology Degree Certificate",
    "Issue_Date": "2025-06-09",
    "Certificate_ID": "CERT-UNI-0012"
  },
  {
    "Full_Name": "Riya Reddy",
    "Roll_Number": "DHT2023013",
    "University_Name": "Global Tech University",
    "College_Name": "School of Engineering",
    "Degree": "B.Tech",
    "Branch_or_Specialization": "Computer Science",
    "Year_of_Passing": 2022,
    "Certificate_Name": "Bachelor of Technology Degree Certificate",
    "Issue_Date": "2022-07-07",
    "Certificate_ID": "CERT-UNI-0013"
  },
  {
    "Full_Name": "Anaya Nair",
    "Roll_Number": "DHT2023014",
    "University_Name": "National University of Technology",
    "College_Name": "School of Sciences",
    "Degree": "M.Tech",
    "Branch_or_Specialization": "Electrical",
    "Year_of_Passing": 2022,
    "Certificate_Name": "Master of Technology Degree Certificate",
    "Issue_Date": "2024-11-30",
    "Certificate_ID": "CERT-UNI-0014"
  },
  {
    "Full_Name": "Ishita Patel",
    "Roll_Number": "DHT2023015",
    "University_Name": "Global Tech University",
    "College_Name": "School of Management",
    "Degree": "MBA",
    "Branch_or_Specialization": "Information Technology",
    "Year_of_Passing": 2022,
    "Certificate_Name": "Master of Business Administration Degree Certificate",
    "Issue_Date": "2025-07-29",
    "Certificate_ID": "CERT-UNI-0015"
  },
  {
    "Full_Name": "Kunal Sharma",
    "Roll_Number": "DHT2023016",
    "University_Name": "Indian Institute of Digital Learning",
    "College_Name": "School of Sciences",
    "Degree": "M.Tech",
    "Branch_or_Specialization": "Marketing",
    "Year_of_Passing": 2023,
    "Certificate_Name": "Master of Technology Degree Certificate",
    "Issue_Date": "2023-05-04",
    "Certificate_ID": "CERT-UNI-0016"
  },
  {
    "Full_Name": "Ishita Singh",
    "Roll_Number": "DHT2023017",
    "University_Name": "National University of Technology",
    "College_Name": "School of Humanities",
    "Degree": "MBA",
    "Branch_or_Specialization": "Electrical",
    "Year_of_Passing": 2023,
    "Certificate_Name": "Master of Business Administration Degree Certificate",
    "Issue_Date": "2023-07-06",
    "Certificate_ID": "CERT-UNI-0017"
  },
  {
    "Full_Name": "_iddharth Sharma",
    "Roll_Number": "DHT2023018",
    "University_Name": "Indian Institute of Digital Learning",
    "College_Name": "School of Commerce",
    "Degree": "M.Tech",
    "Branch_or_Specialization": "Electrical",
    "Year_of_Passing": 2022,
    "Certificate_Name": "Master of Technology Degree Certificate",
    "Issue_Date": "2022-07-19",
    "Certificate_ID": "CERT-UNI-0018"
  },
  {
    "Full_Name": "Kunal Singh",
    "Roll_Number": "DHT2023019",
    "University_Name": "Eastern Institute of Engineering",
    "College_Name": "School of Sciences",
    "Degree": "MBA",
    "Branch_or_Specialization": "Finance",
    "Year_of_Passing": 2025,
    "Certificate_Name": "Master of Business Administration Degree Certificate",
    "Issue_Date": "2022-03-22",
    "Certificate_ID": "CERT-UNI-0019"
  },
  {
    "Full_Name": "Aditya Nair",
    "Roll_Number": "DHT2023020",
    "University_Name": "Eastern Institute of Engineering",
    "College_Name": "School of Management",
    "Degree": "BBA",
    "Branch_or_Specialization": "Information Technology",
    "Year_of_Passing": 2024,
    "Certificate_Name": "Bachelor of Business Administration Degree Certificate",
    "Issue_Date": "2025-11-14",
    "Certificate_ID": "CERT-UNI-0020"
  },
  {
    "Full_Name": "Meera Nair",
    "Roll_Number": "DHT2023021",
    "University_Name": "Eastern Institute of Engineering",
    "College_Name": "School of Management",
    "Degree": "MBA",
    "Branch_or_Specialization": "Mechanical",
    "Year_of_Passing": 2022,
    "Certificate_Name": "Master of Business Administration Degree Certificate",
    "Issue_Date": "2024-12-19",
    "Certificate_ID": "CERT-UNI-0021"
  },
  {
    "Full_Name": "Aarav Khan",
    "Roll_Number": "DHT2023022",
    "University_Name": "National University of Technology",
    "College_Name": "School of Management",
    "Degree": "B.Sc",
    "Branch_or_Specialization": "Finance",
    "Year_of_Passing": 2022,
    "Certificate_Name": "Bachelor of Science Degree Certificate",
    "Issue_Date": "2023-11-19",
    "Certificate_ID": "CERT-UNI-0022"
  },
  {
    "Full_Name": "Meera Reddy",
    "Roll_Number": "DHT2023023",
    "University_Name": "Global Tech University",
    "College_Name": "School of Engineering",
    "Degree": "BBA",
    "Branch_or_Specialization": "Biotechnology",
    "Year_of_Passing": 2022,
    "Certificate_Name": "Bachelor of Business Administration Degree Certificate",
    "Issue_Date": "2023-12-25",
    "Certificate_ID": "CERT-UNI-0023"
  },
  {
    "Full_Name": "Diya Patel",
    "Roll_Number": "DHT2023024",
    "University_Name": "Bright Future Institute",
    "College_Name": "School of Humanities",
    "Degree": "B.Tech",
    "Branch_or_Specialization": "Biotechnology",
    "Year_of_Passing": 2025,
    "Certificate_Name": "Bachelor of Technology Degree Certificate",
    "Issue_Date": "2023-10-27",
    "Certificate_ID": "CERT-UNI-0024"
  },
  {
    "Full_Name": "Kunal Khan",
    "Roll_Number": "DHT2023025",
    "University_Name": "Bright Future Institute",
    "College_Name": "School of Management",
    "Degree": "MBA",
    "Branch_or_Specialization": "Computer Science",
    "Year_of_Passing": 2023,
    "Certificate_Name": "Master of Business Administration Degree Certificate",
    "Issue_Date": "2023-12-14",
    "Certificate_ID": "CERT-UNI-0025"
  },
  {
    "Full_Name": "Diya Singh",
    "Roll_Number": "DHT2023026",
    "University_Name": "Bright Future Institute",
    "College_Name": "School of Sciences",
    "Degree": "M.Tech",
    "Branch_or_Specialization": "Computer Science",
    "Year_of_Passing": 2023,
    "Certificate_Name": "Master of Technology Degree Certificate",
    "Issue_Date": "2022-04-19",
    "Certificate_ID": "CERT-UNI-0026"
  },
  {
    "Full_Name": "Riya Mehta",
    "Roll_Number": "DHT2023027",
    "University_Name": "Eastern Institute of Engineering",
    "College_Name": "School of Engineering",
    "Degree": "BBA",
    "Branch_or_Specialization": "Electrical",
    "Year_of_Passing": 2022,
    "Certificate_Name": "Bachelor of Business Administration Degree Certificate",
    "Issue_Date": "2023-09-27",
    "Certificate_ID": "CERT-UNI-0027"
  },
  {
    "Full_Name": "Diya Verma",
    "Roll_Number": "DHT2023028",
    "University_Name": "Indian Institute of Digital Learning",
    "College_Name": "School of Management",
    "Degree": "BBA",
    "Branch_or_Specialization": "Finance",
    "Year_of_Passing": 2025,
    "Certificate_Name": "Bachelor of Business Administration Degree Certificate",
    "Issue_Date": "2025-04-10",
    "Certificate_ID": "CERT-UNI-0028"
  },
  {
    "Full_Name": "Aditya Nair",
    "Roll_Number": "DHT2023029",
    "University_Name": "National University of Technology",
    "College_Name": "School of Engineering",
    "Degree": "M.Tech",
    "Branch_or_Specialization": "Marketing",
    "Year_of_Passing": 2023,
    "Certificate_Name": "Master of Technology Degree Certificate",
    "Issue_Date": "2023-04-12",
    "Certificate_ID": "CERT-UNI-0029"
  },
  {
    "Full_Name": "Diya Verma",
    "Roll_Number": "DHT2023030",
    "University_Name": "Bright Future Institute",
    "College_Name": "School of Management",
    "Degree": "B.Tech",
    "Branch_or_Specialization": "Electrical",
    "Year_of_Passing": 2022,
    "Certificate_Name": "Bachelor of Technology Degree Certificate",
    "Issue_Date": "2024-03-16",
    "Certificate_ID": "CERT-UNI-0030"
  },
  {
    "Full_Name": "Riya Verma",
    "Roll_Number": "DHT2023031",
    "University_Name": "Eastern Institute of Engineering",
    "College_Name": "School of Engineering",
    "Degree": "M.Tech",
    "Branch_or_Specialization": "Biotechnology",
    "Year_of_Passing": 2025,
    "Certificate_Name": "Master of Technology Degree Certificate",
    "Issue_Date": "2024-07-25",
    "Certificate_ID": "CERT-UNI-0031"
  },
  {
    "Full_Name": "Kunal Patel",
    "Roll_Number": "DHT2023032",
    "University_Name": "Eastern Institute of Engineering",
    "College_Name": "School of Engineering",
    "Degree": "BBA",
    "Branch_or_Specialization": "Civil Engineering",
    "Year_of_Passing": 2022,
    "Certificate_Name": "Bachelor of Business Administration Degree Certificate",
    "Issue_Date": "2023-06-19",
    "Certificate_ID": "CERT-UNI-0032"
  },
  {
    "Full_Name": "Aditya Reddy",
    "Roll_Number": "DHT2023033",
    "University_Name": "Bright Future Institute",
    "College_Name": "School of Commerce",
    "Degree": "M.Tech",
    "Branch_or_Specialization": "Marketing",
    "Year_of_Passing": 2023,
    "Certificate_Name": "Master of Technology Degree Certificate",
    "Issue_Date": "2025-09-03",
    "Certificate_ID": "CERT-UNI-0033"
  },
  {
    "Full_Name": "Ishita Khan",
    "Roll_Number": "DHT2023034",
    "University_Name": "National University of Technology",
    "College_Name": "School of Humanities",
    "Degree": "B.Tech",
    "Branch_or_Specialization": "Biotechnology",
    "Year_of_Passing": 2023,
    "Certificate_Name": "Bachelor of Technology Degree Certificate",
    "Issue_Date": "2022-07-27",
    "Certificate_ID": "CERT-UNI-0034"
  },
  {
    "Full_Name": "Diya Sharma",
    "Roll_Number": "DHT2023035",
    "University_Name": "Global Tech University",
    "College_Name": "School of Humanities",
    "Degree": "B.Tech",
    "Branch_or_Specialization": "Electrical",
    "Year_of_Passing": 2025,
    "Certificate_Name": "Bachelor of Technology Degree Certificate",
    "Issue_Date": "2024-01-19",
    "Certificate_ID": "CERT-UNI-0035"
  },
  {
    "Full_Name": "Kunal Chopra",
    "Roll_Number": "DHT2023036",
    "University_Name": "Indian Institute of Digital Learning",
    "College_Name": "School of Commerce",
    "Degree": "MBA",
    "Branch_or_Specialization": "Electrical",
    "Year_of_Passing": 2022,
    "Certificate_Name": "Master of Business Administration Degree Certificate",
    "Issue_Date": "2022-10-15",
    "Certificate_ID": "CERT-UNI-0036"
  },
  {
    "Full_Name": "Riya Sharma",
    "Roll_Number": "DHT2023037",
    "University_Name": "Eastern Institute of Engineering",
    "College_Name": "School of Sciences",
    "Degree": "MBA",
    "Branch_or_Specialization": "Electrical",
    "Year_of_Passing": 2025,
    "Certificate_Name": "Master of Business Administration Degree Certificate",
    "Issue_Date": "2022-01-17",
    "Certificate_ID": "CERT-UNI-0037"
  },
  {
    "Full_Name": "Ishita Chopra",
    "Roll_Number": "DHT2023038",
    "University_Name": "Bright Future Institute",
    "College_Name": "School of Sciences",
    "Degree": "M.Tech",
    "Branch_or_Specialization": "Biotechnology",
    "Year_of_Passing": 2023,
    "Certificate_Name": "Master of Technology Degree Certificate",
    "Issue_Date": "2022-01-26",
    "Certificate_ID": "CERT-UNI-0038"
  },
  {
    "Full_Name": "_iddharth Reddy",
    "Roll_Number": "DHT2023039",
    "University_Name": "Eastern Institute of Engineering",
    "College_Name": "School of Commerce",
    "Degree": "BBA",
    "Branch_or_Specialization": "Information Technology",
    "Year_of_Passing": 2024,
    "Certificate_Name": "Bachelor of Business Administration Degree Certificate",
    "Issue_Date": "2022-02-16",
    "Certificate_ID": "CERT-UNI-0039"
  },
  {
    "Full_Name": "Riya Nair",
    "Roll_Number": "DHT2023040",
    "University_Name": "Global Tech University",
    "College_Name": "School of Management",
    "Degree": "M.Tech",
    "Branch_or_Specialization": "Marketing",
    "Year_of_Passing": 2024,
    "Certificate_Name": "Master of Technology Degree Certificate",
    "Issue_Date": "2024-02-17",
    "Certificate_ID": "CERT-UNI-0040"
  },
  {
    "Full_Name": "Riya Reddy",
    "Roll_Number": "DHT2023041",
    "University_Name": "National University of Technology",
    "College_Name": "School of Engineering",
    "Degree": "MBA",
    "Branch_or_Specialization": "Computer Science",
    "Year_of_Passing": 2022,
    "Certificate_Name": "Master of Business Administration Degree Certificate",
    "Issue_Date": "2025-04-19",
    "Certificate_ID": "CERT-UNI-0041"
  },
  {
    "Full_Name": "_iddharth Nair",
    "Roll_Number": "DHT2023042",
    "University_Name": "Indian Institute of Digital Learning",
    "College_Name": "School of Sciences",
    "Degree": "M.Tech",
    "Branch_or_Specialization": "Marketing",
    "Year_of_Passing": 2023,
    "Certificate_Name": "Master of Technology Degree Certificate",
    "Issue_Date": "2023-11-07",
    "Certificate_ID": "CERT-UNI-0042"
  },
  {
    "Full_Name": "Vivaan Reddy",
    "Roll_Number": "DHT2023043",
    "University_Name": "Bright Future Institute",
    "College_Name": "School of Sciences",
    "Degree": "MBA",
    "Branch_or_Specialization": "Computer Science",
    "Year_of_Passing": 2022,
    "Certificate_Name": "Master of Business Administration Degree Certificate",
    "Issue_Date": "2024-12-27",
    "Certificate_ID": "CERT-UNI-0043"
  },
  {
    "Full_Name": "Vivaan Khan",
    "Roll_Number": "DHT2023044",
    "University_Name": "National University of Technology",
    "College_Name": "School of Engineering",
    "Degree": "M.Tech",
    "Branch_or_Specialization": "Civil Engineering",
    "Year_of_Passing": 2024,
    "Certificate_Name": "Master of Technology Degree Certificate",
    "Issue_Date": "2025-09-21",
    "Certificate_ID": "CERT-UNI-0044"
  },
  {
    "Full_Name": "Ishita Verma",
    "Roll_Number": "DHT2023045",
    "University_Name": "Indian Institute of Digital Learning",
    "College_Name": "School of Sciences",
    "Degree": "M.Tech",
    "Branch_or_Specialization": "Finance",
    "Year_of_Passing": 2025,
    "Certificate_Name": "Master of Technology Degree Certificate",
    "Issue_Date": "2022-03-16",
    "Certificate_ID": "CERT-UNI-0045"
  },
  {
    "Full_Name": "_iddharth Das",
    "Roll_Number": "DHT2023046",
    "University_Name": "Global Tech University",
    "College_Name": "School of Humanities",
    "Degree": "B.Tech",
    "Branch_or_Specialization": "Mechanical",
    "Year_of_Passing": 2023,
    "Certificate_Name": "Bachelor of Technology Degree Certificate",
    "Issue_Date": "2023-10-11",
    "Certificate_ID": "CERT-UNI-0046"
  },
  {
    "Full_Name": "_iddharth Mehta",
    "Roll_Number": "DHT2023047",
    "University_Name": "National University of Technology",
    "College_Name": "School of Humanities",
    "Degree": "M.Tech",
    "Branch_or_Specialization": "Marketing",
    "Year_of_Passing": 2023,
    "Certificate_Name": "Master of Technology Degree Certificate",
    "Issue_Date": "2023-10-05",
    "Certificate_ID": "CERT-UNI-0047"
  },
  {
    "Full_Name": "Anaya Reddy",
    "Roll_Number": "DHT2023048",
    "University_Name": "Global Tech University",
    "College_Name": "School of Engineering",
    "Degree": "B.Sc",
    "Branch_or_Specialization": "Marketing",
    "Year_of_Passing": 2025,
    "Certificate_Name": "Bachelor of Science Degree Certificate",
    "Issue_Date": "2022-09-11",
    "Certificate_ID": "CERT-UNI-0048"
  },
  {
    "Full_Name": "Kunal Khan",
    "Roll_Number": "DHT2023049",
    "University_Name": "Indian Institute of Digital Learning",
    "College_Name": "School of Management",
    "Degree": "M.Tech",
    "Branch_or_Specialization": "Computer Science",
    "Year_of_Passing": 2023,
    "Certificate_Name": "Master of Technology Degree Certificate",
    "Issue_Date": "2022-05-21",
    "Certificate_ID": "CERT-UNI-0049"
  },
  {
    "Full_Name": "Aditya Khan",
    "Roll_Number": "DHT2023050",
    "University_Name": "Eastern Institute of Engineering",
    "College_Name": "School of Humanities",
    "Degree": "B.Tech",
    "Branch_or_Specialization": "Electrical",
    "Year_of_Passing": 2023,
    "Certificate_Name": "Bachelor of Technology Degree Certificate",
    "Issue_Date": "2023-12-12",
    "Certificate_ID": "CERT-UNI-0050"
  }
]